mm_solana_cli/__init__.py
mm_solana_cli/cli.py
mm_solana_cli/helpers.py
mm_solana_cli/cmd/balance_cmd.py
mm_solana_cli/cmd/example_cmd.py
mm_solana_cli/cmd/node_cmd.py
mm_solana_cli/cmd/transfer_sol_cmd.py
mm_solana_cli/cmd/wallet/__init__.py
mm_solana_cli/cmd/wallet/keypair_cmd.py
mm_solana_cli/cmd/wallet/new_cmd.py
mm_solana_cli/examples/balance.yml
mm_solana_cli/examples/transfer-sol.yml
mm_solana_cli-0.1.1.dist-info/METADATA
mm_solana_cli-0.1.1.dist-info/WHEEL
mm_solana_cli-0.1.1.dist-info/entry_points.txt
mm_solana_cli-0.1.1.dist-info/RECORD
